LICENSE.txt
MANIFEST.in
README
setup.py
docs/history.rst
docs/index.rst
docs/installation.rst
docs/usage.rst
redsolutioncms.django_tinymce.egg-info/PKG-INFO
redsolutioncms.django_tinymce.egg-info/SOURCES.txt
redsolutioncms.django_tinymce.egg-info/dependency_links.txt
redsolutioncms.django_tinymce.egg-info/entry_points.txt
redsolutioncms.django_tinymce.egg-info/not-zip-safe
redsolutioncms.django_tinymce.egg-info/top_level.txt
testtinymce/testapp/__init__.py
testtinymce/testapp/admin.py
testtinymce/testapp/models.py
testtinymce/testapp/views.py
tinymce/__init__.py
tinymce/compressor.py
tinymce/models.py
tinymce/settings.py
tinymce/urls.py
tinymce/views.py
tinymce/widgets.py
tinymce/redsolution_setup/__init__.py
tinymce/redsolution_setup/make.py
tinymce/redsolution_setup/templates/tinymce/redsolutioncms/settings.pyt
tinymce/redsolution_setup/templates/tinymce/redsolutioncms/urls.pyt
tinymce/static/tinymce/jscripts/tiny_mce/tiny_mce.js
tinymce/static/tinymce/jscripts/tiny_mce/tiny_mce_popup.js
tinymce/static/tinymce/jscripts/tiny_mce/tiny_mce_src.js
tinymce/static/tinymce/jscripts/tiny_mce/langs/en.js
tinymce/static/tinymce/jscripts/tiny_mce/langs/ru.js
tinymce/static/tinymce/jscripts/tiny_mce/plugins/advhr/editor_plugin.js
tinymce/static/tinymce/jscripts/tiny_mce/plugins/advhr/editor_plugin_src.js
tinymce/static/tinymce/jscripts/tiny_mce/plugins/advhr/rule.htm
tinymce/static/tinymce/jscripts/tiny_mce/plugins/advhr/css/advhr.css
tinymce/static/tinymce/jscripts/tiny_mce/plugins/advhr/js/rule.js
tinymce/static/tinymce/jscripts/tiny_mce/plugins/advhr/langs/en_dlg.js
tinymce/static/tinymce/jscripts/tiny_mce/plugins/advhr/langs/ru_dlg.js
tinymce/static/tinymce/jscripts/tiny_mce/plugins/advimage/editor_plugin.js
tinymce/static/tinymce/jscripts/tiny_mce/plugins/advimage/editor_plugin_src.js
tinymce/static/tinymce/jscripts/tiny_mce/plugins/advimage/image.htm
tinymce/static/tinymce/jscripts/tiny_mce/plugins/advimage/css/advimage.css
tinymce/static/tinymce/jscripts/tiny_mce/plugins/advimage/img/sample.gif
tinymce/static/tinymce/jscripts/tiny_mce/plugins/advimage/js/image.js
tinymce/static/tinymce/jscripts/tiny_mce/plugins/advimage/langs/en_dlg.js
tinymce/static/tinymce/jscripts/tiny_mce/plugins/advimage/langs/ru_dlg.js
tinymce/static/tinymce/jscripts/tiny_mce/plugins/advlink/editor_plugin.js
