Metadata-Version: 1.0
Name: redsolutioncms.django-tinymce
Version: 1.5.1
Summary: Use the TinyMCE WYSIWYG editor for your form textareas. 
Home-page: http://code.google.com/p/django-tinymce/
Author: Joost Cassee
Author-email: joost@cassee.net
License: MIT License
Download-URL: http://code.google.com/p/django-tinymce/downloads/list
Keywords: django widget tinymce
Platform: UNKNOWN
Classifier: Development Status :: 3 - Alpha
Classifier: Intended Audience :: Developers
Classifier: License :: Freely Distributable
Classifier: Framework :: Django
Classifier: Environment :: Web Environment
Classifier: Natural Language :: Russian
Classifier: Natural Language :: English
Classifier: Operating System :: OS Independent
Classifier: Programming Language :: Python
Classifier: Topic :: Internet :: WWW/HTTP :: Site Management
